askfia_api/__init__.py
askfia_api/auth.py
askfia_api/config.py
askfia_api/main.py
askfia_api/api/__init__.py
askfia_api/api/routes/__init__.py
askfia_api/api/routes/auth.py
askfia_api/api/routes/chat.py
askfia_api/api/routes/downloads.py
askfia_api/api/routes/health.py
askfia_api/api/routes/query.py
askfia_api/api/routes/usage.py
askfia_api/models/__init__.py
askfia_api/models/schemas.py
askfia_api/services/__init__.py
askfia_api/services/agent.py
askfia_api/services/fia_service.py
askfia_api/services/forest_types.py
askfia_api/services/species_data.py
askfia_api/services/storage.py
askfia_api/services/usage_tracker.py
askfia_api-0.2.1.dist-info/METADATA
askfia_api-0.2.1.dist-info/WHEEL
askfia_api-0.2.1.dist-info/RECORD
